{"100012":["education"],"100022":["social-psychology"],"100032":["education"],"100042":["education"],"100052":["information","education"],"100062":["literature-history-philosophy"],"100072":["earth-environment","literature-history-philosophy"],"100082":["foreign-languages"],"100092":["foreign-languages"],"100102":["management"],"100112":["finance-economics"],"100122":["management"],"100132":["information","management"],"100142":["information","management"],"100152":["management"],"100162":["finance-economics"],"100172":["finance-economics"],"100182":["bio-resources"],"100192":["bio-resources"],"100202":["bio-resources"],"100212":["bio-resources"],"100222":["bio-resources"],"100232":["life-science"],"100242":["architecture-design"],"100252":["life-science","bio-resources"],"100262":["math-chemistry"],"100272":["math-chemistry"],"100282":["math-chemistry"],"100292":["information","engineering"],"100302":["information","engineering"],"100312":["engineering"],"100322":["engineering"],"100332":["information","engineering"],"100342":["engineering"],"100352":["life-science","bio-resources"],"100362":["life-science"],"100372":["life-science"],"100382":["math-chemistry","life-science"],"100392":["life-science"],"100402":["health-medicine","bio-resources"],"100412":["arts"],"100422":["arts"],"100432":["arts"],"100442":["recreation-sports"],"101012":["foreign-languages"],"101022":["management","recreation-sports"],"101032":["foreign-languages"],"101042":["foreign-languages"],"101052":["foreign-languages"],"101062":["law-politics"],"101072":["law-politics"],"101082":["law-politics"],"101092":["finance-economics"],"101102":["management"],"101112":["engineering","management"],"101122":["information","management"],"101132":["information","management"],"101142":["finance-economics"],"101152":["finance-economics"],"101162":["math-chemistry"],"101172":["math-chemistry"],"101182":["math-chemistry"],"101192":["life-science"],"101202":["information","engineering"],"101212":["engineering"],"101222":["engineering","earth-environment"],"101232":["engineering"],"101242":["information","engineering"],"101252":["information","engineering"],"101262":["engineering","architecture-design"],"101272":["architecture-design","arts"],"108012":["health-medicine"],"108022":["health-medicine"],"108032":["health-medicine"],"108042":["health-medicine"],"108052":["health-medicine"],"108062":["health-medicine"],"108072":["life-science"],"108082":["health-medicine"],"108092":["health-medicine"],"108102":["information","life-science"],"108112":["engineering","life-science"],"108122":["mass-communication"],"108132":["social-psychology"],"108142":["social-psychology"],"108152":["social-psychology"],"108162":["foreign-languages"],"108172":["foreign-languages"],"108182":["information","management"],"108192":["health-medicine","management"],"108202":["management"],"108212":["management","recreation-sports"],"108222":["health-medicine"],"109012":["health-medicine"],"109022":["health-medicine"],"109032":["health-medicine"],"109042":["health-medicine"],"109052":["health-medicine"],"109062":["health-medicine"],"109072":["health-medicine"],"109082":["health-medicine"],"109092":["health-medicine"],"109102":["health-medicine"],"109112":["health-medicine","management"],"109122":["health-medicine"],"109132":["health-medicine"],"109142":["health-medicine"],"109152":["health-medicine"],"109162":["engineering","life-science"],"109172":["life-science","bio-resources"],"109182":[],"109192":[],"109202":[],"109212":[],"109222":[],"110012":["management"],"110022":["management"],"110032":["management","finance-economics"],"110042":["management","finance-economics"],"110052":["engineering","management"],"110062":["engineering","management"],"110072":["management","recreation-sports"],"110082":["management","recreation-sports"],"110092":["management","recreation-sports"],"110102":["information","management"],"110112":["information","management"],"110122":["information","management"],"110132":["information","mass-communication"],"110142":["information","architecture-design"],"110152":["law-politics"],"110162":["foreign-languages"],"110172":["foreign-languages"],"110182":["foreign-languages"],"110192":["health-medicine"],"110202":["health-medicine"],"110212":[],"110222":[],"112012":["education"],"112022":["health-medicine"],"113012":["finance-economics"],"113022":["law-politics"],"113032":["management"],"113042":["finance-economics"],"113052":["information","management"],"113062":["management","recreation-sports"],"113072":["finance-economics"],"130012":["engineering","architecture-design"],"130022":["engineering","architecture-design"],"130032":["mass-communication"],"130042":["mass-communication"],"130052":["mass-communication"],"130062":["information","management"],"130072":["information","management"],"130082":["information","management"],"130092":["information","management"],"130102":["foreign-languages"],"130112":["foreign-languages"],"130122":["foreign-languages"],"130132":["foreign-languages"],"130142":["literature-history-philosophy"],"130152":["social-psychology"],"130162":["social-psychology"],"130172":["social-psychology"],"130182":["law-politics","management"],"130192":["law-politics","management"],"130202":["law-politics","management"],"130212":["law-politics","management"],"130222":["management","recreation-sports"],"130232":["management"],"130242":["finance-economics"],"130252":["management","finance-economics"],"130262":[],"130272":[],"130282":["management","recreation-sports"],"130292":["architecture-design","arts"],"130302":["architecture-design","arts"],"134012":["health-medicine","management"],"134022":["health-medicine","management"],"134032":["health-medicine"],"134042":["health-medicine"],"134052":["health-medicine"],"134062":["health-medicine"],"134072":["social-psychology"],"134082":["social-psychology"],"134092":["social-psychology"],"134102":["social-psychology"],"134112":["health-medicine"],"134122":["health-medicine"],"134132":["health-medicine"],"134142":["health-medicine"],"134152":["health-medicine"],"134162":["health-medicine"],"134172":["health-medicine"],"134182":["health-medicine"],"134192":["information","life-science"],"134202":["engineering","life-science"],"134212":["information","engineering"],"134222":["information","engineering"],"134232":["information","engineering"],"134242":["information","engineering"],"134252":["information","architecture-design"],"134262":["information","mass-communication"],"134272":["management"],"134282":["management"],"134292":["finance-economics"],"134302":["finance-economics"],"134312":["finance-economics"],"134322":["law-politics"],"134332":["social-psychology"],"134342":["social-psychology"],"134352":["education"],"134362":["information","architecture-design"],"134372":["information","architecture-design"],"134382":["architecture-design","arts"],"134392":["architecture-design","arts"],"134402":["architecture-design"],"150012":["foreign-languages"],"150022":["finance-economics"],"150032":["management","recreation-sports"],"150042":["engineering"],"150052":["engineering"],"150062":["engineering"],"150072":["engineering","earth-environment"],"150082":["engineering"],"150092":["life-science","bio-resources"],"150102":["bio-resources"],"150112":["bio-resources"],"150122":["bio-resources"],"150132":["information","engineering"],"150142":["information","engineering"],"150152":["information","engineering"],"150162":["information","engineering"],"150172":["information","engineering"],"151012":["engineering"],"151022":["engineering"],"151032":["engineering"],"151042":["engineering"],"151052":["engineering","earth-environment"],"151062":["engineering","earth-environment"],"151072":["engineering","architecture-design"],"151082":["architecture-design","arts"],"151092":["information","engineering"],"151102":["information","engineering"],"151112":["information","engineering"],"151122":["information","engineering"],"151132":["information","engineering"],"151142":["management"],"151152":["information","management"],"151162":["information","management"],"151172":["finance-economics"],"151182":["literature-history-philosophy"],"151192":["literature-history-philosophy","education"],"151202":["management","recreation-sports"],"151212":["literature-history-philosophy","management"],"152012":["health-medicine"],"152022":["health-medicine"],"152032":["health-medicine"],"152042":["health-medicine"],"152052":["health-medicine"],"152062":["health-medicine"],"152072":["health-medicine"],"152082":["health-medicine"],"152092":["health-medicine"],"152102":["health-medicine"],"152112":["health-medicine"],"152122":["health-medicine"],"153012":["foreign-languages"],"153022":["management","recreation-sports"],"153032":["management"],"153042":["information","engineering"],"153052":["information","engineering"],"153062":["life-science","bio-resources"],"153072":["engineering"],"153082":["management","recreation-sports"],"153092":["information","engineering"],"153102":["information","engineering"],"153112":["information","engineering"],"153122":["engineering","architecture-design"],"153132":["law-politics"],"153142":["literature-history-philosophy"],"153152":["law-politics","management"],"153162":["engineering","management"],"153172":["health-medicine"],"153182":["health-medicine"],"153192":["health-medicine"],"153202":["social-psychology"],"153212":["architecture-design"],"154012":[],"154022":[],"001012":["literature-history-philosophy"],"001022":["foreign-languages"],"001032":["literature-history-philosophy"],"001042":["literature-history-philosophy"],"001052":["social-psychology"],"001062":["information","literature-history-philosophy"],"001072":["foreign-languages"],"001082":["arts"],"001092":["math-chemistry"],"001102":["math-chemistry"],"001112":["math-chemistry"],"001122":["earth-environment"],"001132":["social-psychology"],"001142":["earth-environment"],"001152":["earth-environment"],"001162":["law-politics"],"001172":["law-politics"],"001182":["law-politics"],"001192":["finance-economics"],"001202":["finance-economics"],"001212":["finance-economics"],"001222":["social-psychology"],"001232":["social-psychology"],"001242":["health-medicine"],"001252":["health-medicine"],"001262":["health-medicine"],"001272":["health-medicine"],"001282":["health-medicine"],"001292":["health-medicine"],"001302":["health-medicine"],"001312":["health-medicine"],"001322":["engineering"],"001332":["engineering"],"001342":["engineering"],"001352":["engineering","earth-environment"],"001362":["engineering"],"001372":["engineering","life-science"],"001382":["bio-resources"],"001392":["engineering","earth-environment"],"001402":["math-chemistry","life-science"],"001412":["bio-resources"],"001422":["bio-resources"],"001432":["finance-economics"],"001442":["bio-resources"],"001452":["health-medicine","bio-resources"],"001462":["mass-communication"],"001472":["engineering"],"001482":["life-science","bio-resources"],"001492":["life-science","bio-resources"],"001502":["management"],"001512":["management"],"001522":["finance-economics"],"001532":["finance-economics"],"001542":["management","finance-economics"],"001552":["information","management"],"001562":["information","management"],"001572":["health-medicine"],"001582":["information","engineering"],"001592":["information","engineering"],"001602":["information","engineering"],"001612":["information","engineering"],"001622":["law-politics"],"001632":["law-politics"],"001642":["law-politics"],"001652":["life-science"],"001662":["math-chemistry","life-science"],"001672":["management","recreation-sports"],"002012":["education"],"002022":["social-psychology"],"002032":["education"],"002042":["education"],"002052":["health-medicine"],"002062":["social-psychology"],"002072":["social-psychology"],"002082":["social-psychology"],"002092":["education"],"002102":["education"],"002112":["education"],"002122":["education"],"002132":["education"],"002142":["education"],"002152":["literature-history-philosophy"],"002162":["foreign-languages"],"002172":["literature-history-philosophy"],"002182":["earth-environment"],"002192":["literature-history-philosophy"],"002202":["math-chemistry"],"002212":["math-chemistry"],"002222":["math-chemistry"],"002232":["math-chemistry"],"002242":["math-chemistry"],"002252":["life-science"],"002262":["earth-environment"],"002272":["information","engineering"],"002282":["information","engineering"],"002292":["information","engineering"],"002302":["health-medicine"],"002312":["engineering","education"],"002322":["mass-communication"],"002332":["engineering"],"002342":["information","engineering"],"002352":["information","engineering"],"002362":["literature-history-philosophy","education"],"002372":["law-politics"],"002382":["management"],"002392":["architecture-design","arts"],"002402":["education"],"002412":["life-science"],"002422":["information","engineering"],"002432":["management"],"002442":["arts"],"002452":["arts"],"002472":["architecture-design","arts"],"002482":["arts"],"002492":["arts"],"002502":["recreation-sports"],"002512":["recreation-sports"],"002522":["recreation-sports"],"003012":["literature-history-philosophy"],"003022":["foreign-languages"],"003032":["literature-history-philosophy"],"003042":["literature-history-philosophy"],"003052":["finance-economics"],"003062":["management"],"003072":["information","management"],"003082":["information","management"],"003092":["finance-economics"],"003102":["management"],"003112":["finance-economics"],"003122":["law-politics"],"003132":["math-chemistry"],"003142":["math-chemistry"],"003152":["math-chemistry"],"003162":["math-chemistry"],"003172":["math-chemistry"],"003182":["math-chemistry"],"003192":["engineering"],"003202":["engineering"],"003212":["engineering","earth-environment"],"003222":["engineering"],"003232":["engineering"],"003242":["engineering"],"003252":["information","engineering"],"003262":["information","engineering"],"003272":["information","engineering"],"003282":["information","engineering"],"003292":["information","engineering"],"003302":["engineering"],"003312":["engineering","earth-environment"],"003322":["life-science","bio-resources"],"003332":["bio-resources"],"003342":["bio-resources"],"003352":["bio-resources"],"003362":["bio-resources"],"003372":["life-science","bio-resources"],"003382":["life-science","bio-resources"],"003392":["bio-resources"],"003402":["math-chemistry","life-science"],"003412":["life-science"],"003422":["architecture-design"],"003432":["management"],"003442":["life-science"],"003452":["health-medicine","bio-resources"],"004012":["literature-history-philosophy"],"004022":["foreign-languages"],"004032":["literature-history-philosophy"],"004042":["literature-history-philosophy"],"004052":["math-chemistry"],"004062":["math-chemistry"],"004072":["math-chemistry"],"004082":["earth-environment"],"004092":["information","engineering"],"004102":["engineering"],"004112":["engineering"],"004122":["engineering"],"004132":["engineering"],"004142":["engineering","earth-environment"],"004152":["engineering"],"004162":["engineering","earth-environment"],"004172":["engineering","earth-environment"],"004182":["engineering","earth-environment"],"004192":["engineering"],"004202":["engineering"],"004212":["engineering","earth-environment"],"004222":["engineering"],"004232":["engineering","life-science"],"004242":["information","management"],"004252":["information","management"],"004262":["engineering","management"],"004272":["information","math-chemistry"],"004282":["finance-economics"],"004292":["management"],"004302":["health-medicine"],"004312":["health-medicine"],"004322":["health-medicine"],"004332":["health-medicine"],"004342":["health-medicine"],"004352":["health-medicine"],"004362":["health-medicine"],"004372":["health-medicine"],"004382":["law-politics"],"004392":["finance-economics"],"004402":["law-politics"],"004412":["social-psychology"],"004422":["information","engineering"],"004432":["information","engineering"],"004442":["information","engineering"],"004452":["information","engineering"],"004462":["information","engineering"],"004472":["engineering","architecture-design"],"004482":["architecture-design"],"004492":["architecture-design","arts"],"004502":["life-science"],"004512":["life-science"],"004522":["life-science"],"004532":[],"005012":["literature-history-philosophy"],"005022":["literature-history-philosophy"],"005032":["literature-history-philosophy"],"005042":["law-politics"],"005052":["social-psychology"],"005062":["social-psychology"],"005072":["foreign-languages"],"005082":["foreign-languages"],"005092":["foreign-languages"],"005102":["math-chemistry"],"005112":["math-chemistry"],"005122":["math-chemistry"],"005132":["life-science"],"005142":["social-psychology"],"005152":["law-politics"],"005162":["finance-economics"],"005172":["finance-economics"],"005182":["management"],"005192":["management","finance-economics"],"005202":["finance-economics"],"005212":["information","management"],"005222":["information","management"],"005232":["information","math-chemistry"],"005242":["arts"],"006012":["literature-history-philosophy"],"006022":["literature-history-philosophy"],"006032":["literature-history-philosophy"],"006042":["education"],"006052":["law-politics"],"006062":["social-psychology"],"006072":["finance-economics"],"006082":["law-politics","management"],"006092":["architecture-design"],"006102":["law-politics","management"],"006112":["engineering"],"006122":["finance-economics"],"006132":["social-psychology"],"006142":["law-politics"],"006152":["management","finance-economics"],"006162":["finance-economics"],"006172":["finance-economics"],"006182":["information","math-chemistry"],"006192":["information","math-chemistry"],"006202":["management"],"006212":["information","management"],"006222":["finance-economics"],"006232":["finance-economics"],"006242":["mass-communication"],"006252":["mass-communication"],"006262":["foreign-languages"],"006272":["foreign-languages"],"006282":["foreign-languages"],"006292":["foreign-languages"],"006302":["foreign-languages"],"006312":["foreign-languages"],"006322":["foreign-languages"],"006332":["foreign-languages"],"006342":["foreign-languages"],"006352":["foreign-languages"],"006362":["foreign-languages"],"006372":["foreign-languages"],"006382":["law-politics"],"006392":["math-chemistry"],"006402":["social-psychology"],"006412":["information","engineering"],"006422":["information","engineering"],"006432":["information","engineering"],"006442":[],"007012":["health-medicine"],"007022":["health-medicine","recreation-sports"],"007032":["health-medicine"],"007042":["health-medicine"],"007052":["health-medicine"],"007062":["health-medicine"],"007072":["health-medicine"],"007082":["health-medicine"],"007092":["health-medicine"],"007102":["health-medicine"],"007112":["health-medicine"],"007122":["health-medicine"],"007132":["health-medicine"],"007142":["health-medicine","management"],"007152":["health-medicine","management"],"007162":["math-chemistry"],"007172":["math-chemistry"],"007182":["life-science"],"007192":["life-science"],"007202":["life-science"],"007212":["social-psychology"],"007222":["social-psychology"],"007232":["health-medicine"],"007242":["health-medicine"],"007252":["health-medicine"],"007272":["health-medicine"],"007312":["health-medicine"],"008012":["math-chemistry"],"008022":["math-chemistry"],"008032":["engineering"],"008042":["math-chemistry"],"008052":["math-chemistry"],"008062":["social-psychology"],"008072":["life-science"],"008082":["engineering"],"008092":["engineering"],"008102":["engineering"],"008112":["engineering"],"008122":["engineering"],"008132":["engineering","life-science"],"008142":["engineering","earth-environment"],"008152":["information","engineering"],"008162":["engineering","management"],"008172":["engineering","management"],"008182":["information","engineering"],"008192":["information","engineering"],"008202":["information","engineering"],"008212":["information","engineering"],"008222":["information","engineering"],"008232":["management"],"008242":["management"],"008252":["management"],"008262":["management","finance-economics"],"008272":["finance-economics"],"008282":["information","management"],"008292":["finance-economics"],"008302":["management"],"008312":["law-politics"],"008322":["law-politics"],"008332":["engineering","architecture-design"],"008342":["architecture-design"],"008352":["architecture-design","arts"],"008362":["architecture-design","arts"],"008372":["architecture-design"],"008382":["engineering","architecture-design"],"008392":["education"],"008402":["foreign-languages"],"008412":["literature-history-philosophy","education"],"008422":["architecture-design","arts"],"009012":["literature-history-philosophy"],"009022":["foreign-languages"],"009032":["literature-history-philosophy"],"009042":["foreign-languages"],"009052":["literature-history-philosophy"],"009062":["math-chemistry"],"009072":["math-chemistry"],"009082":["math-chemistry"],"009092":["life-science"],"009102":["life-science","bio-resources"],"009112":["math-chemistry"],"009122":["math-chemistry"],"009132":["engineering"],"009142":["engineering","management"],"009152":["engineering","management"],"009162":["engineering","earth-environment"],"009172":["information","engineering"],"009182":["information","engineering"],"009192":["information","engineering"],"009202":["management"],"009212":["management","finance-economics"],"009222":["finance-economics"],"009232":["finance-economics"],"009242":["information","math-chemistry"],"009252":["information","math-chemistry"],"009262":["information","management"],"009272":["finance-economics"],"009282":["law-politics"],"009292":["law-politics","management"],"009302":["social-psychology"],"009312":["social-psychology"],"009322":["bio-resources"],"009332":["life-science","bio-resources"],"009342":["management","recreation-sports"],"009352":["health-medicine"],"009362":["engineering","architecture-design"],"009372":["architecture-design","arts"],"009382":["architecture-design","arts"],"009392":["architecture-design"],"009402":["law-politics"],"009412":["management","finance-economics"],"009422":["math-chemistry"],"009432":["arts"],"009442":["arts"],"009452":["arts"],"011012":["literature-history-philosophy"],"011022":["literature-history-philosophy"],"011032":["foreign-languages"],"011042":["social-psychology"],"011052":["education"],"011062":["education"],"011072":["social-psychology"],"011082":["social-psychology"],"011092":["social-psychology"],"011102":["education"],"011112":["foreign-languages","education"],"011122":["education"],"011132":["literature-history-philosophy","management"],"011142":["finance-economics"],"011152":[],"011162":["finance-economics"],"011172":["math-chemistry"],"011182":["math-chemistry"],"011192":["math-chemistry"],"011202":["math-chemistry"],"011212":["math-chemistry"],"011222":["math-chemistry"],"011232":["math-chemistry"],"011242":["engineering","life-science"],"011252":["engineering","earth-environment"],"011262":["engineering","earth-environment"],"011272":["engineering","earth-environment"],"011282":["engineering"],"011292":["engineering"],"011302":["engineering"],"011312":["engineering","management"],"011322":["engineering"],"011332":["information","engineering"],"011342":["information","engineering"],"011352":["information","engineering"],"011362":["information","engineering"],"011372":["information","engineering"],"011382":["information","engineering"],"011392":["information","engineering"],"011402":["life-science"],"011412":["life-science"],"011422":["life-science"],"011432":[],"011442":[],"011492":["recreation-sports"],"011502":["arts"],"011512":["arts"],"011522":["arts"],"011532":["arts"],"011542":["architecture-design","arts"],"011552":["architecture-design","arts"],"012012":["health-medicine"],"012022":["health-medicine"],"012032":["health-medicine"],"012042":["health-medicine"],"012052":["health-medicine"],"012062":["health-medicine"],"012072":["health-medicine"],"012082":["health-medicine"],"012092":["health-medicine"],"012102":["life-science"],"012112":["health-medicine","recreation-sports"],"012122":["health-medicine"],"012132":["health-medicine"],"012142":["health-medicine"],"012152":["health-medicine"],"012162":["engineering","life-science"],"012172":["information","life-science"],"013012":["information","engineering"],"013022":["information","engineering"],"013032":["information","engineering"],"013042":["information","engineering"],"013052":["information","engineering"],"013062":["information","engineering"],"013072":["information","engineering"],"013082":["information","engineering"],"013092":["information","engineering"],"013102":["information","engineering"],"013112":["information","engineering"],"013122":["engineering"],"013132":["engineering"],"013142":["engineering"],"013152":["engineering"],"013162":["math-chemistry"],"013172":["math-chemistry"],"013182":["math-chemistry"],"013192":["math-chemistry"],"013202":["math-chemistry"],"013212":["math-chemistry"],"013222":["life-science"],"013232":["life-science"],"013242":["information","management"],"013252":["finance-economics"],"013262":["management"],"013272":["engineering","management"],"013282":["engineering","management"],"013292":["foreign-languages"],"013302":["foreign-languages"],"013312":["mass-communication"],"013322":["social-psychology"],"013342":["engineering"],"013382":["health-medicine"],"013392":["health-medicine"],"013422":["health-medicine"],"013432":["health-medicine"],"013442":["health-medicine"],"013452":["health-medicine"],"013462":["health-medicine"],"013472":["health-medicine"],"013482":["health-medicine"],"013492":["health-medicine"],"013502":["health-medicine"],"013512":["health-medicine"],"013522":["life-science"],"013532":["life-science"],"013542":["engineering","life-science"],"013552":["health-medicine"],"013562":[],"013572":["health-medicine"],"014012":["literature-history-philosophy"],"014022":["literature-history-philosophy"],"014032":["information","literature-history-philosophy"],"014042":["mass-communication"],"014052":["information","mass-communication"],"014062":["information","education"],"014072":["education"],"014082":["foreign-languages"],"014092":["foreign-languages"],"014102":["foreign-languages"],"014112":["foreign-languages"],"014122":["foreign-languages"],"014132":["foreign-languages"],"014142":["foreign-languages"],"014152":["finance-economics"],"014162":["finance-economics"],"014172":["management","finance-economics"],"014182":["management","finance-economics"],"014192":["finance-economics"],"014202":["finance-economics"],"014212":["finance-economics"],"014222":["management"],"014232":["management"],"014242":["information","math-chemistry"],"014252":["information","management"],"014262":["engineering","management"],"014272":["law-politics","management"],"014282":["management"],"014292":["law-politics"],"014302":["management","recreation-sports"],"014312":["law-politics","management"],"014322":["math-chemistry"],"014332":["math-chemistry"],"014342":["math-chemistry"],"014352":["math-chemistry"],"014362":["engineering","architecture-design"],"014372":["engineering"],"014382":["information","engineering"],"014392":["information","engineering"],"014402":["engineering"],"014412":["information","engineering"],"014422":["information","engineering"],"014432":["information","engineering"],"014442":["engineering"],"014452":["engineering"],"014462":["engineering","earth-environment"],"014472":["information","engineering"],"014482":["information","engineering"],"014492":["information","engineering"],"014502":["information","engineering"],"014512":["information","management"],"014522":["engineering","architecture-design"],"015012":["engineering"],"015022":["engineering"],"015032":["engineering","management"],"015042":["engineering","management"],"015052":["engineering"],"015062":["engineering"],"015072":["engineering"],"015082":["math-chemistry"],"015092":["math-chemistry"],"015102":["engineering"],"015112":["engineering","earth-environment"],"015122":["information","engineering"],"015132":["finance-economics"],"015142":["management","finance-economics"],"015152":["management","finance-economics"],"015162":["finance-economics"],"015172":["management"],"015182":["information","math-chemistry"],"015192":["information","math-chemistry"],"015202":["finance-economics"],"015212":["management"],"015222":["management"],"015232":["literature-history-philosophy"],"015242":["foreign-languages"],"015252":["information","engineering"],"015262":["information","engineering"],"015272":["information","engineering"],"015282":["information","engineering"],"015292":["information","engineering"],"015302":["information","engineering"],"015312":["information","engineering"],"015322":["information","engineering"],"015332":["engineering"],"015342":["engineering","earth-environment"],"015352":["architecture-design"],"015362":["engineering","management"],"015372":["law-politics","management"],"015382":["finance-economics"],"015392":["finance-economics"],"015402":["finance-economics"],"015412":["finance-economics"],"015422":["architecture-design"],"015432":["engineering","architecture-design"],"015442":["management"],"015452":["management"],"015462":["architecture-design","arts"],"015472":["information","engineering"],"015482":["information","engineering"],"015492":["management"],"015502":["information","engineering"],"015512":["information","engineering"],"015522":["information","management"],"016012":["literature-history-philosophy"],"016022":["foreign-languages"],"016032":["foreign-languages"],"016042":["literature-history-philosophy"],"016052":["math-chemistry"],"016062":["math-chemistry"],"016072":["math-chemistry"],"016082":["math-chemistry"],"016092":["information","engineering"],"016102":["math-chemistry"],"016112":["engineering"],"016122":["engineering"],"016132":["engineering"],"016142":["engineering"],"016152":["engineering"],"016162":["engineering"],"016172":["management"],"016182":["information","management"],"016192":["information","management"],"016202":["finance-economics"],"016212":["finance-economics"],"016222":["information","engineering"],"016232":["information","engineering"],"016242":["information","engineering"],"016252":["information","engineering"],"016262":["information","engineering"],"016272":["information","engineering"],"016282":["earth-environment"],"016292":["engineering"],"016302":["earth-environment"],"016312":["earth-environment"],"016322":["literature-history-philosophy"],"016332":["social-psychology"],"016342":["life-science"],"016352":["engineering","life-science"],"017012":["literature-history-philosophy"],"017022":["literature-history-philosophy"],"017032":["literature-history-philosophy"],"017042":["foreign-languages"],"017052":["foreign-languages"],"017062":["foreign-languages"],"017072":["management","finance-economics"],"017082":["information","math-chemistry"],"017092":["math-chemistry"],"017102":["math-chemistry"],"017112":["earth-environment"],"017122":["earth-environment"],"017132":["life-science"],"017142":["law-politics"],"017152":["law-politics"],"017162":["management"],"017172":["social-psychology","management"],"017182":["social-psychology"],"017192":["law-politics","management"],"017202":["life-science","bio-resources"],"017212":["bio-resources"],"017222":["bio-resources"],"017232":["law-politics","management"],"017242":["social-psychology"],"017252":["health-medicine"],"017262":["engineering"],"017272":["information","engineering"],"017282":["engineering"],"017292":["engineering"],"017302":["information","engineering"],"017312":["management","finance-economics"],"017322":["management","finance-economics"],"017332":["finance-economics"],"017342":["management","recreation-sports"],"017352":["information","management"],"017362":["information","management"],"017372":["finance-economics"],"017382":["finance-economics"],"017392":["finance-economics"],"017402":["management"],"017412":["mass-communication"],"017422":["mass-communication"],"017432":["information","mass-communication"],"017442":["mass-communication"],"017452":["architecture-design"],"017462":["engineering","architecture-design"],"017472":["architecture-design"],"017482":["education"],"017492":["social-psychology"],"017502":["arts"],"017512":["arts"],"017522":["arts"],"017532":["arts"],"017542":["arts"],"017552":["arts"],"018012":["foreign-languages"],"018022":["foreign-languages"],"018032":["foreign-languages"],"018042":["literature-history-philosophy"],"018052":["social-psychology"],"018062":["literature-history-philosophy"],"018072":["law-politics"],"018082":["life-science","bio-resources"],"018092":["mass-communication"],"018102":["finance-economics"],"018112":["math-chemistry"],"018122":["health-medicine"],"018132":["health-medicine"],"018142":["information","math-chemistry"],"018152":["engineering"],"018162":["management"],"018172":["management","finance-economics"],"018182":["finance-economics"],"018192":["management","recreation-sports"],"018202":["finance-economics"],"018212":["information","management"],"018222":["information","management"],"018232":["information","management"],"018242":["information","management"],"018252":["information","engineering"],"018262":["information","engineering"],"018272":["information","engineering"],"018282":["information","mass-communication"],"018292":["information","mass-communication"],"018302":["information","mass-communication"],"018312":["information","engineering"],"018322":["management"],"018332":["foreign-languages"],"018342":["information","architecture-design"],"019012":["engineering","earth-environment"],"019022":["engineering"],"019032":["engineering"],"019042":["information","engineering"],"019052":["information","engineering"],"019062":["information","management"],"019072":["foreign-languages"],"019082":["architecture-design","arts"],"019092":["information","architecture-design"],"019102":["information","architecture-design"],"019112":["information","engineering"],"020012":["literature-history-philosophy"],"020022":["literature-history-philosophy"],"020032":["literature-history-philosophy"],"020042":["literature-history-philosophy"],"020052":["architecture-design"],"020062":["architecture-design"],"020072":["mass-communication"],"020082":["mass-communication"],"020092":["mass-communication"],"020102":["information","literature-history-philosophy"],"020112":["education"],"020122":["health-medicine"],"020132":["health-medicine"],"020142":["health-medicine"],"020152":["health-medicine"],"020162":["health-medicine"],"020172":["social-psychology"],"020182":["health-medicine"],"020192":["health-medicine"],"020202":["math-chemistry"],"020212":["math-chemistry"],"020222":["math-chemistry"],"020232":["information","engineering"],"020242":["information","engineering"],"020252":["life-science"],"020262":["life-science"],"020272":["math-chemistry"],"020282":["math-chemistry"],"020292":["information","engineering"],"020302":["information","engineering"],"020312":["information","engineering"],"020322":["information","engineering"],"020332":["information","engineering"],"020342":["information","engineering"],"020352":["foreign-languages"],"020362":["foreign-languages"],"020372":["foreign-languages"],"020382":["foreign-languages"],"020392":["foreign-languages"],"020402":["foreign-languages"],"020412":["foreign-languages"],"020422":["architecture-design","arts"],"020432":["architecture-design","arts"],"020442":["management"],"020452":["management","recreation-sports"],"020462":["social-psychology"],"020472":["life-science","bio-resources"],"020482":["health-medicine"],"020492":["law-politics"],"020502":["law-politics"],"020512":["management"],"020522":["finance-economics"],"020532":["information","management"],"020542":["information","management"],"020552":["information","math-chemistry"],"020562":["management","finance-economics"],"020572":["social-psychology"],"020582":["social-psychology"],"020592":["finance-economics"],"020602":["social-psychology","literature-history-philosophy"],"020612":["social-psychology"],"020622":["social-psychology","literature-history-philosophy"],"020632":["arts"],"020642":["arts"],"020652":["arts"],"020662":["architecture-design","arts"],"020672":["recreation-sports"],"020682":["recreation-sports"],"021012":["engineering","management"],"021022":["engineering","management"],"021032":["engineering","management"],"021042":["engineering","management"],"021052":["engineering"],"021062":["life-science","bio-resources"],"021072":["bio-resources"],"021082":["life-science"],"021092":["engineering","earth-environment"],"021102":["engineering","earth-environment"],"021112":["engineering"],"021122":["earth-environment"],"021132":["bio-resources"],"021142":["information","engineering"],"021152":["information","engineering"],"021162":["information","engineering"],"021172":["information","engineering"],"021182":["information","engineering"],"021192":["information","engineering"],"021202":["information","engineering"],"021212":["management","recreation-sports"],"021222":["management","recreation-sports"],"021232":["law-politics"],"021242":["law-politics"],"021252":["architecture-design","arts"],"021262":["engineering","management"],"021272":["engineering"],"021282":["life-science"],"022012":["literature-history-philosophy"],"022022":["foreign-languages"],"022032":["earth-environment"],"022042":["math-chemistry"],"022052":["math-chemistry"],"022062":["math-chemistry"],"022072":["math-chemistry"],"022082":["life-science"],"022092":["education"],"022102":["education"],"022112":["management"],"022122":["engineering","education"],"022132":["engineering","education"],"022142":["architecture-design","arts"],"022152":["architecture-design","arts"],"022162":["information","engineering"],"022172":["information","engineering"],"022182":["information","engineering"],"022192":["information","engineering"],"022202":["information","engineering"],"022212":["arts"],"022222":["arts"],"022232":["architecture-design","arts"],"022242":["recreation-sports"],"023012":["social-psychology"],"023022":["social-psychology"],"023032":["education"],"023042":["math-chemistry"],"023052":["math-chemistry"],"023062":["math-chemistry"],"023072":["life-science"],"023082":["math-chemistry"],"023092":["foreign-languages"],"023102":["literature-history-philosophy"],"023112":["earth-environment"],"023122":["engineering"],"023132":["information","engineering"],"023142":["information","engineering"],"023152":["information","engineering"],"023162":["information","engineering"],"023172":["information","engineering"],"023182":["management"],"023192":["finance-economics"],"023202":["information","management"],"023212":["information","management"],"023222":["education"],"023232":["law-politics","management"],"023292":["arts"],"023302":["arts"],"023312":["recreation-sports"],"023322":["recreation-sports"],"026012":["health-medicine"],"026022":["health-medicine"],"026032":["health-medicine"],"026042":["health-medicine"],"026052":["health-medicine"],"026062":["health-medicine"],"026072":["life-science"],"026082":["health-medicine"],"026092":["health-medicine"],"026102":["social-psychology"],"026112":["health-medicine"],"026122":["health-medicine"],"026132":["health-medicine"],"026142":["math-chemistry"],"026152":["math-chemistry"],"026162":["life-science","bio-resources"],"026172":["health-medicine"],"026182":["health-medicine"],"026192":["foreign-languages"],"026202":["health-medicine"],"026212":["health-medicine"],"026222":["social-psychology"],"026232":["information","life-science"],"026242":["information","life-science"],"026252":["health-medicine","management"],"027012":["literature-history-philosophy"],"027022":["foreign-languages"],"027032":["arts"],"027042":["life-science"],"027052":["life-science"],"027062":["math-chemistry"],"027072":["math-chemistry"],"027082":["math-chemistry"],"027092":["math-chemistry"],"027102":["math-chemistry"],"027112":["math-chemistry"],"027122":["information","engineering"],"027132":["information","engineering"],"027142":["information","engineering"],"027152":["engineering"],"027162":["engineering"],"027172":["information","engineering"],"027182":["information","engineering"],"027192":["information","engineering"],"027202":["information","engineering"],"027212":["engineering"],"027222":["engineering"],"027232":["management"],"027242":["information","management"],"027252":["finance-economics"],"027262":["management","finance-economics"],"027272":["bio-resources"],"027282":["engineering","earth-environment"],"027292":["earth-environment"],"027302":["law-politics","management"],"027312":["social-psychology"],"027322":[],"027332":["life-science"],"027342":["engineering","life-science"],"027352":["health-medicine"],"027442":["arts"],"027452":["arts"],"028012":["arts"],"028022":["arts"],"028032":["arts"],"030012":["health-medicine"],"030022":["health-medicine"],"030032":["health-medicine"],"030042":["health-medicine"],"030052":["health-medicine"],"030062":["health-medicine"],"030072":["health-medicine"],"030082":["health-medicine"],"030092":["life-science"],"030102":["health-medicine"],"030112":["information","engineering"],"030122":["engineering"],"030132":["engineering"],"030142":["engineering"],"030152":["information","engineering"],"030162":["information","engineering"],"030172":["engineering","life-science"],"030182":["engineering","life-science"],"030192":["information","engineering"],"030202":["health-medicine","management"],"030212":["management"],"030222":["architecture-design","arts"],"030232":["architecture-design","arts"],"030242":["information","management"],"030252":["information","management"],"030262":["finance-economics"],"030272":["finance-economics"],"031012":[],"031022":["education"],"031032":["education"],"031042":["education"],"031062":["recreation-sports"],"031072":["literature-history-philosophy","education"],"031082":["literature-history-philosophy","management"],"031092":["social-psychology"],"031102":["social-psychology"],"031112":["literature-history-philosophy"],"031122":["foreign-languages"],"031132":["math-chemistry","education"],"031142":["math-chemistry"],"031152":["information","engineering"],"031162":["information","engineering"],"031172":["information","engineering"],"031182":["management","finance-economics"],"031192":["literature-history-philosophy","management"],"031202":["arts"],"031212":["arts"],"031222":["arts"],"031232":["recreation-sports"],"032012":["education"],"032022":["education"],"032032":["education"],"032042":["education"],"032052":["education"],"032062":["education"],"032072":["education"],"032082":["education"],"032092":["social-psychology"],"032102":["social-psychology"],"032112":["social-psychology"],"032122":["earth-environment","literature-history-philosophy"],"032132":["foreign-languages","education"],"032142":["foreign-languages","education"],"032152":["education"],"032162":["literature-history-philosophy"],"032172":["literature-history-philosophy","management"],"032182":["literature-history-philosophy","management"],"032192":["math-chemistry","education"],"032202":["information","education"],"032212":["information","education"],"032222":["information","education"],"032232":["math-chemistry"],"032242":["math-chemistry"],"032252":["information","engineering"],"032262":["information","architecture-design"],"032272":["information","architecture-design"],"032282":["architecture-design","arts"],"032292":["architecture-design","arts"],"032302":["recreation-sports"],"032312":["recreation-sports"],"032322":["recreation-sports"],"033012":["education"],"033022":["social-psychology"],"033032":["education"],"033042":["education"],"033052":["education"],"033062":["earth-environment","literature-history-philosophy"],"033072":["literature-history-philosophy"],"033082":["foreign-languages"],"033092":["math-chemistry"],"033102":["information","education"],"033112":["information","education"],"033122":["engineering"],"033132":["information","engineering"],"033142":["information","engineering"],"033152":["information","engineering"],"033162":["information","engineering"],"033172":["engineering","earth-environment"],"033182":["life-science"],"033192":["life-science","bio-resources"],"033202":["arts"],"033212":["law-politics","management"],"033222":["management"],"033232":["arts"],"033242":["arts"],"033252":["arts"],"033262":["recreation-sports"],"034012":["math-chemistry"],"034022":["information","math-chemistry"],"034032":["math-chemistry"],"034042":["math-chemistry"],"034052":["math-chemistry"],"034062":["life-science"],"034072":["information","engineering"],"034082":["information","engineering"],"034092":["information","engineering"],"034102":["information","engineering"],"034112":["information","engineering"],"034122":["information","engineering"],"034132":["information","engineering"],"034142":["engineering"],"034152":["information","engineering"],"034162":["information","math-chemistry"],"034172":["management"],"034182":["management"],"034192":["finance-economics"],"034202":["information","management"],"034212":["information","management"],"034222":["information","management"],"034232":["management","finance-economics"],"034242":["finance-economics"],"034252":["management","recreation-sports"],"034262":["management"],"034272":["management"],"034282":["management"],"034292":["management"],"034302":["literature-history-philosophy"],"034312":["literature-history-philosophy"],"034322":["foreign-languages"],"034332":["earth-environment","literature-history-philosophy"],"034342":["literature-history-philosophy"],"034352":["finance-economics"],"034362":["social-psychology"],"034372":["social-psychology"],"034382":["law-politics","management"],"034392":["law-politics"],"034402":["education"],"034412":["education"],"034422":["education"],"034432":["education"],"034442":["social-psychology"],"034452":["mass-communication"],"034462":["social-psychology"],"034472":["social-psychology"],"034482":["arts"],"034492":["earth-environment"],"034502":[],"034512":["arts"],"034522":["architecture-design","arts"],"034532":["literature-history-philosophy","management"],"034542":["recreation-sports"],"035012":["education"],"035022":["education"],"035032":["education"],"035042":["social-psychology"],"035052":["information","education"],"035062":["literature-history-philosophy"],"035072":["foreign-languages","education"],"035082":["law-politics","management"],"035092":["earth-environment","literature-history-philosophy"],"035102":["math-chemistry"],"035112":["math-chemistry"],"035122":["math-chemistry"],"035132":["math-chemistry"],"035142":["information","engineering"],"035152":["information","engineering"],"035162":["information","engineering"],"035172":["architecture-design"],"035182":["management"],"035192":["health-medicine"],"035202":["arts"],"035212":["architecture-design","arts"],"035222":["recreation-sports"],"035232":["management","recreation-sports"],"035242":["health-medicine","recreation-sports"],"036012":["education"],"036022":["education"],"036032":["education"],"036042":["social-psychology"],"036052":["social-psychology"],"036062":["literature-history-philosophy"],"036072":["literature-history-philosophy","management"],"036082":["social-psychology"],"036092":["foreign-languages"],"036102":["foreign-languages"],"036112":["foreign-languages"],"036122":["management"],"036132":["management"],"036142":["management"],"036152":["finance-economics"],"036162":["management","recreation-sports"],"036172":["law-politics","management"],"036182":["management","finance-economics"],"036192":["finance-economics"],"036202":["math-chemistry"],"036212":["math-chemistry"],"036222":["math-chemistry"],"036232":["math-chemistry"],"036242":["mass-communication"],"036252":["information","engineering"],"036262":["information","engineering"],"036272":["information","engineering"],"036282":["information","engineering"],"036292":["information","engineering"],"036302":["information","management"],"036312":["arts"],"036322":["arts"],"036332":["architecture-design","arts"],"036342":["architecture-design","arts"],"036352":["recreation-sports"],"038012":[],"038022":["education"],"038032":["education"],"038042":["education"],"038052":["management","recreation-sports"],"038062":["information","architecture-design"],"038072":["law-politics","management"],"038082":["management","recreation-sports"],"038092":["foreign-languages"],"038102":["literature-history-philosophy"],"038112":["life-science"],"038122":["information","engineering"],"038132":["information","management"],"038142":["math-chemistry"],"038152":["math-chemistry"],"038162":["math-chemistry"],"038172":["information","engineering"],"038182":["arts"],"038192":["arts"],"038202":["architecture-design","arts"],"038212":["recreation-sports"],"039012":["management","recreation-sports"],"039022":["management","recreation-sports"],"039032":["health-medicine","recreation-sports"],"039042":["health-medicine","recreation-sports"],"039052":["management","recreation-sports"],"039062":["management","recreation-sports"],"039072":["management","recreation-sports"],"039082":["recreation-sports"],"040012":["health-medicine"],"040022":["management"],"040032":["finance-economics"],"040042":["management","finance-economics"],"040052":["finance-economics"],"040062":["management"],"040072":["foreign-languages"],"040082":["literature-history-philosophy"],"040092":["social-psychology"],"040102":["social-psychology"],"040112":["information","management"],"040122":["information","management"],"040132":["information","mass-communication"],"040142":["information","mass-communication"],"040152":["information","engineering"],"040162":["information","engineering"],"040172":["information","engineering"],"040182":["information","management"],"040192":["engineering"],"040202":["engineering"],"040212":["engineering","management"],"040222":["engineering","management"],"040232":["information","engineering"],"040242":["information","engineering"],"040252":["information","engineering"],"040262":["information","engineering"],"040272":["information","engineering"],"040282":["architecture-design","arts"],"040292":["information","mass-communication"],"041012":["literature-history-philosophy"],"041022":["foreign-languages"],"041032":["literature-history-philosophy"],"041042":["literature-history-philosophy"],"041052":["math-chemistry"],"041062":["earth-environment"],"041072":["math-chemistry"],"041082":["math-chemistry"],"041092":["life-science"],"041102":["social-psychology"],"041112":["social-psychology"],"041122":["social-psychology","management"],"041132":["law-politics"],"041142":["mass-communication"],"041152":["information","engineering"],"041162":["information","engineering"],"041172":["engineering"],"041182":["engineering"],"041192":["engineering"],"041202":["engineering"],"041212":["information","engineering"],"041222":["finance-economics"],"041232":["finance-economics"],"041242":["management"],"041252":["finance-economics"],"041262":["information","management"],"041272":["information","management"],"041282":["law-politics"],"041292":["law-politics"],"041302":["law-politics"],"041312":["education"],"041322":["social-psychology","law-politics"],"041332":[],"042012":["engineering"],"042022":["engineering"],"042032":["information","engineering"],"042042":["information","engineering"],"042052":["information","engineering"],"042062":["information","engineering"],"042072":["information","engineering"],"042082":["information","engineering"],"042092":["information","engineering"],"042102":["information","engineering"],"042112":["engineering","earth-environment"],"042122":["engineering","earth-environment"],"042132":["management"],"042142":["information","management"],"042152":["information","management"],"042162":["finance-economics"],"042172":["finance-economics"],"042182":["finance-economics"],"042192":["foreign-languages"],"042202":["foreign-languages"],"042212":["life-science"],"042222":["life-science"],"042232":["health-medicine"],"042242":["health-medicine"],"042252":["management","recreation-sports"],"042262":["management","recreation-sports"],"042272":["management","recreation-sports"],"042282":["health-medicine"],"042292":["health-medicine"],"042302":["health-medicine"],"042312":["engineering","life-science"],"042322":["engineering","life-science"],"042332":["health-medicine"],"042342":["health-medicine"],"042352":["architecture-design","arts"],"042362":["architecture-design","arts"],"042372":["arts"],"042382":["information","architecture-design"],"042392":["information","architecture-design"],"042402":["information","architecture-design"],"042412":["information","architecture-design"],"042422":["architecture-design"],"042432":["architecture-design"],"042442":["health-medicine","recreation-sports"],"043012":["information","engineering"],"043022":["information","engineering"],"043032":["information","engineering"],"043042":["information","engineering"],"043052":["information","engineering"],"043062":["information","engineering"],"043072":["information","engineering"],"043082":["engineering","management"],"043092":["engineering","management"],"043102":["information","management"],"043112":["information","management"],"043122":["information","management"],"043132":["management"],"043142":["management"],"043152":["management"],"043162":["engineering","architecture-design"],"043172":["engineering","architecture-design"],"043182":["engineering"],"043192":["foreign-languages"],"043202":["foreign-languages"],"043212":["foreign-languages","management"],"043222":["management","recreation-sports"],"043232":["management","recreation-sports"],"043242":["management","recreation-sports"],"043252":["management"],"043262":["information","management"],"043272":["information","management"],"043282":["management","recreation-sports"],"044012":["information","management"],"044022":["information","engineering"],"044032":["architecture-design"],"044042":["architecture-design"],"044052":["architecture-design","arts"],"044062":["architecture-design","arts"],"044072":["information","architecture-design"],"044082":["social-psychology","literature-history-philosophy"],"044092":["arts"],"044102":["architecture-design","arts"],"044112":["arts"],"045012":["information","engineering"],"045022":["information","engineering"],"045032":["information","engineering"],"045042":["information","engineering"],"045052":["information","engineering"],"045062":["information","engineering"],"045072":["engineering"],"045082":["engineering"],"045092":["engineering"],"045102":["engineering"],"045112":["engineering","life-science"],"045122":["information","engineering"],"045132":["information","engineering"],"045142":["information","management"],"045152":["management"],"045162":["finance-economics"],"045172":["finance-economics"],"045182":["management","finance-economics"],"045192":["health-medicine","management"],"045202":["management","recreation-sports"],"045212":["management","recreation-sports"],"045222":["management","finance-economics"],"045232":["finance-economics"],"045242":["management","recreation-sports"],"045252":["mass-communication","management"],"045262":["foreign-languages"],"045272":["mass-communication"],"045282":["mass-communication"],"045292":["architecture-design","arts"],"045302":["life-science"],"045312":["life-science"],"045322":["health-medicine"],"045332":["health-medicine"],"045342":["health-medicine"],"045352":["health-medicine"],"045362":["health-medicine"],"045372":["health-medicine"],"045382":["health-medicine"],"046012":["management"],"046022":["management"],"046032":["management"],"046042":["finance-economics"],"046052":["finance-economics"],"046062":["finance-economics"],"046072":["finance-economics"],"046082":["finance-economics"],"046092":["management","finance-economics"],"046102":["management","finance-economics"],"046112":["mass-communication"],"046122":["mass-communication"],"046132":["mass-communication"],"046142":["mass-communication"],"046152":["law-politics"],"046162":["law-politics"],"046172":["management","finance-economics"],"046182":["mass-communication"],"046192":["management"],"046202":["law-politics"],"046212":["information","management"],"046222":["literature-history-philosophy","education"],"046232":["literature-history-philosophy","education"],"046242":["foreign-languages"],"046252":["foreign-languages"],"046262":["architecture-design","arts"],"046272":["architecture-design","arts"],"046282":["information","architecture-design"],"046292":["engineering","architecture-design"],"046302":["architecture-design"],"046312":["architecture-design"],"046322":["management","recreation-sports"],"046332":["management","recreation-sports"],"046342":["management","recreation-sports"],"046352":["social-psychology","law-politics"],"046362":["law-politics","management"],"046372":["social-psychology"],"046382":["finance-economics"],"046392":["finance-economics"],"046402":["information","management"],"046412":["information","management"],"046422":["information","management"],"046432":["information","engineering"],"046442":["information","engineering"],"046452":["information","engineering"],"046462":["information","engineering"],"046472":["information","engineering"],"046482":["information","health-medicine","management"],"046492":["information","health-medicine","management"],"046502":["life-science"],"046512":["life-science"],"046522":["engineering","life-science"],"046532":["engineering","life-science"],"046542":["management","finance-economics"],"046552":["mass-communication"],"046562":["foreign-languages"],"047012":["mass-communication"],"047022":["mass-communication"],"047032":["mass-communication"],"047042":["mass-communication"],"047052":["architecture-design","arts"],"047062":["mass-communication"],"047072":["mass-communication"],"047082":["information","mass-communication"],"047092":["information","architecture-design"],"047102":["mass-communication"],"047112":["information","management"],"047122":["information","management"],"047132":["information","management"],"047142":["information","management"],"047152":["finance-economics"],"047162":["law-politics","management"],"047172":["management","recreation-sports"],"047182":["management","recreation-sports"],"047192":["finance-economics"],"047202":["management"],"047212":["social-psychology"],"047222":["foreign-languages"],"047232":["foreign-languages"],"047242":["law-politics"],"050012":["health-medicine"],"050022":["health-medicine","life-science","bio-resources"],"050032":["social-psychology"],"050042":["social-psychology"],"050052":["social-psychology"],"050062":["social-psychology"],"050072":["social-psychology"],"050082":["management","recreation-sports"],"050092":["management","recreation-sports"],"050102":["law-politics"],"050112":["architecture-design","arts"],"050122":["architecture-design","arts"],"050132":["architecture-design","arts"],"050142":["architecture-design","arts"],"050152":["architecture-design","arts"],"050162":["architecture-design","arts"],"050172":["engineering","architecture-design"],"050182":["finance-economics"],"050192":["finance-economics"],"050202":["management","finance-economics"],"050212":["management","finance-economics"],"050222":["management","finance-economics"],"050232":["management","finance-economics"],"050242":["management"],"050252":["management"],"050262":["management"],"050272":["management"],"050282":["finance-economics"],"050292":["finance-economics"],"050302":["finance-economics"],"050312":["foreign-languages"],"050322":["foreign-languages"],"050332":["information","management"],"050342":["information","management"],"050352":["information","management"],"050362":["information","management"],"050372":["information","management"],"050382":["information","management"],"050392":["management","finance-economics"],"050402":["management","finance-economics"],"050412":["management"],"050422":["management"],"050432":["management","finance-economics"],"050442":["management","finance-economics"],"050452":["management","finance-economics"],"050462":["management","finance-economics"],"050472":["finance-economics"],"050482":["finance-economics"],"050492":["finance-economics"],"050502":["finance-economics"],"050512":["finance-economics"],"050522":["information","management"],"050532":["information","management"],"050542":["information","management"],"050552":["information","engineering"],"050562":["information","engineering"],"050572":["information","engineering"],"050582":["information","engineering"],"050592":["architecture-design","arts"],"050602":["architecture-design","arts"],"050612":["architecture-design","arts"],"050622":["management","recreation-sports"],"050632":["management","recreation-sports"],"050642":["management","recreation-sports"],"050652":["management","recreation-sports"],"050662":["management","recreation-sports"],"050672":["foreign-languages"],"050682":["literature-history-philosophy"],"050692":["literature-history-philosophy"],"050702":["literature-history-philosophy"],"050712":["arts"],"050722":["arts"],"050732":["architecture-design","arts"],"050742":["architecture-design","arts"],"050752":["information","architecture-design"],"050762":["information","architecture-design"],"050772":["information","architecture-design"],"050782":["information","architecture-design"],"050792":["architecture-design","arts"],"050802":["architecture-design","arts"],"050812":["architecture-design","arts"],"050822":["architecture-design","arts"],"050832":["management","recreation-sports"],"051012":["management"],"051022":["management"],"051032":["management"],"051042":["management"],"051052":["management","finance-economics"],"051062":["management","finance-economics"],"051072":["management","finance-economics"],"051082":["finance-economics"],"051092":["finance-economics"],"051102":["finance-economics"],"051112":["engineering","management"],"051122":["law-politics","management"],"051132":["law-politics","management"],"051142":["finance-economics"],"051152":["finance-economics"],"051162":["finance-economics"],"051172":["finance-economics"],"051182":["management","recreation-sports"],"051192":["management","recreation-sports"],"051202":["management","recreation-sports"],"051212":["management","recreation-sports"],"051222":["health-medicine","management"],"051232":["health-medicine","management"],"051242":["life-science"],"051252":["life-science"],"051262":["life-science"],"051272":["social-psychology"],"051282":["health-medicine"],"051292":["health-medicine"],"051302":["health-medicine"],"051312":["health-medicine"],"051322":["health-medicine"],"051332":["health-medicine"],"051342":["health-medicine"],"051352":["health-medicine"],"051362":["health-medicine"],"051372":["health-medicine"],"051382":["earth-environment"],"051392":["earth-environment"],"051402":["earth-environment"],"051412":["earth-environment"],"051422":["engineering","earth-environment"],"051432":["engineering","earth-environment"],"051442":["engineering","earth-environment"],"051452":["earth-environment"],"051462":["mass-communication"],"051472":["foreign-languages"],"051482":["foreign-languages"],"051492":["social-psychology"],"051502":["social-psychology"],"051512":["foreign-languages"],"051522":["foreign-languages"],"051532":["information","architecture-design"],"051542":["information","architecture-design"],"051552":["information","engineering"],"051562":["arts"],"051572":["arts"],"051582":["arts"],"051592":["arts"],"051602":["recreation-sports"],"056012":["mass-communication"],"056022":["mass-communication"],"056032":["mass-communication"],"056042":["arts"],"056052":["arts"],"056062":["arts"],"056072":["arts"],"056082":["arts"],"056092":["arts"],"056102":["arts"],"056112":["arts"],"056122":["arts"],"056132":["arts"],"056142":["arts"],"056152":["arts"],"056162":["arts"],"056172":["architecture-design","arts"],"056182":["architecture-design","arts"],"056192":["architecture-design","arts"],"056202":["architecture-design","arts"],"056212":["arts","recreation-sports"],"058012":["literature-history-philosophy"],"058022":["foreign-languages"],"058032":["social-psychology"],"058042":["law-politics","management"],"058052":["literature-history-philosophy"],"058062":["law-politics"],"058072":["management","finance-economics"],"058082":["finance-economics"],"058092":["information","management"],"058102":["information","management"],"058112":["finance-economics"],"058122":["management","recreation-sports"],"058132":["management","recreation-sports"],"058142":[],"058152":["education"],"058162":["education"],"058172":["social-psychology"],"058182":["education"],"058192":["education"],"058202":["education"],"058212":["information","engineering"],"058222":["information","engineering"],"058232":["information","engineering"],"058242":["engineering"],"058252":["information","engineering"],"058262":["math-chemistry"],"058272":["engineering"],"058282":["engineering"],"058292":["engineering"],"058302":["health-medicine"],"059012":["finance-economics"],"059022":["finance-economics"],"059032":["finance-economics"],"059042":["management"],"059052":["management"],"059062":["management"],"059072":["management"],"059082":["literature-history-philosophy","management"],"059092":["literature-history-philosophy","management"],"059102":["management","recreation-sports"],"059112":["management","recreation-sports"],"059122":["management","recreation-sports"],"059132":["management","recreation-sports"],"059142":["management","finance-economics"],"059152":["management","finance-economics"],"059162":["social-psychology","literature-history-philosophy"],"059172":["social-psychology","literature-history-philosophy"],"059182":["social-psychology"],"059192":["education"],"059202":["literature-history-philosophy"],"059212":["literature-history-philosophy"],"059222":["foreign-languages"],"059232":["foreign-languages"],"059242":["social-psychology"],"059252":["social-psychology"],"059262":["social-psychology"],"059272":["social-psychology"],"059282":["social-psychology"],"059292":["social-psychology"],"059302":["mass-communication"],"059312":["mass-communication"],"059322":["mass-communication"],"059332":["law-politics"],"059342":["law-politics"],"059352":["law-politics"],"059362":["architecture-design","arts"],"059372":["architecture-design","arts"],"059382":["arts"],"059392":["engineering","architecture-design"],"059402":["engineering","architecture-design"],"059412":["engineering","architecture-design"],"059422":["architecture-design","arts"],"059432":["architecture-design","arts"],"059442":["information","engineering"],"059452":["information","engineering"],"059462":["information","engineering"],"059472":["information","engineering"],"059482":["life-science"],"059492":["life-science"],"059502":["life-science"],"059512":["information","management"],"059522":["information","management"],"059532":["information","management"],"060012":["recreation-sports"],"060022":["management","recreation-sports"],"060032":["management","recreation-sports"],"060042":["health-medicine","recreation-sports"],"060052":["health-medicine","recreation-sports"],"060062":["information","mass-communication"],"060072":["recreation-sports"],"063012":["arts","literature-history-philosophy"],"063022":["arts","literature-history-philosophy"],"063032":["arts"],"063042":["architecture-design","arts"],"065012":["social-psychology"],"065022":["social-psychology"],"065032":["law-politics"],"065042":["mass-communication"],"065052":["foreign-languages"],"065062":["management","recreation-sports"],"065072":["architecture-design","arts"],"065082":["architecture-design","arts"],"079012":["literature-history-philosophy","management"],"079022":["literature-history-philosophy","management"],"079032":["social-psychology","literature-history-philosophy"],"079042":["social-psychology","literature-history-philosophy"],"079052":["social-psychology","literature-history-philosophy"],"079062":["social-psychology","literature-history-philosophy"],"079072":["foreign-languages"],"079082":["foreign-languages"],"079092":["information","math-chemistry","finance-economics"],"079102":["information","math-chemistry","finance-economics"],"079112":["information","engineering"],"079122":["information","engineering"],"079132":["information","engineering"],"079142":["law-politics"],"079152":["law-politics"],"079162":["finance-economics"],"079172":["management","finance-economics"],"079182":["management","finance-economics"],"079192":["finance-economics"],"079202":["management"],"079212":["management"],"079222":["management","recreation-sports"],"079232":["information","mass-communication"],"079242":["management","recreation-sports"],"079252":["management","recreation-sports"],"079262":["engineering","management"],"079272":["arts"],"079282":["arts"],"099012":["law-politics"],"099022":["law-politics"],"099032":["law-politics"],"099042":["law-politics"],"099052":["law-politics"],"099062":["law-politics"],"099072":["management"],"099082":["management"],"099092":["finance-economics"],"099102":["finance-economics"],"099112":["finance-economics"],"099122":["finance-economics"],"099132":["information","math-chemistry"],"099142":["information","math-chemistry"],"099152":["management","recreation-sports"],"099162":["management","recreation-sports"],"099172":["law-politics","management"],"099182":["law-politics","management"],"099192":["finance-economics"],"099202":["finance-economics"],"099212":["law-politics","management"],"099222":["law-politics","management"],"099232":["law-politics","management"],"099242":["finance-economics"],"099252":["finance-economics"],"099262":["social-psychology"],"099272":["social-psychology"],"099282":["social-psychology"],"099292":["social-psychology"],"099302":["literature-history-philosophy"],"099312":["literature-history-philosophy"],"099322":["foreign-languages"],"099332":["foreign-languages"],"099342":["literature-history-philosophy"],"099352":["literature-history-philosophy"],"099362":["information","engineering"],"099372":["information","engineering"],"099382":["information","engineering"],"099392":["information","engineering"],"099402":["information","engineering"],"099412":["information","engineering"],"099422":["information","engineering"],"001742":["health-medicine","life-science","bio-resources"],"001682":["arts","social-psychology","foreign-languages","literature-history-philosophy","law-politics"],"001722":["information","engineering","management"],"001752":["health-medicine"],"001732":["management","finance-economics"],"001702":["math-chemistry","social-psychology"],"001712":["health-medicine","life-science"],"001692":["mass-communication"],"003472":["foreign-languages","literature-history-philosophy","law-politics"],"003492":["information","engineering"],"003482":["math-chemistry"],"003502":["life-science","bio-resources"],"003512":["health-medicine","life-science","bio-resources"],"004542":["foreign-languages","literature-history-philosophy","law-politics"],"004562":["information","engineering","math-chemistry","earth-environment"],"004572":["information","engineering","architecture-design"],"004582":["math-chemistry","health-medicine","life-science","social-psychology"],"006452":["social-psychology","literature-history-philosophy","education","law-politics"],"006462":["information","math-chemistry","social-psychology","management","finance-economics"],"007262":["health-medicine"],"007282":["social-psychology"],"007292":["life-science"],"007302":["health-medicine","management"],"011452":["finance-economics"],"002462":["arts"],"003462":["information","management","finance-economics"],"011472":["engineering","math-chemistry","life-science","finance-economics"],"011462":["finance-economics"],"004552":["information","engineering","management","finance-economics"],"011482":["information","engineering","finance-economics"],"013332":["information","engineering"],"013352":["life-science"],"013362":["information","management","finance-economics"],"013372":["foreign-languages"],"013402":["health-medicine"],"013412":["engineering","life-science"],"016362":["information","engineering"],"016372":["information","management","finance-economics"],"016382":["information","engineering","math-chemistry","life-science","earth-environment"],"016402":["social-psychology","foreign-languages","literature-history-philosophy"],"016392":["engineering","math-chemistry"],"023242":["education","law-politics","management"],"023252":["earth-environment","foreign-languages","literature-history-philosophy"],"023262":["information","management","finance-economics"],"023272":["math-chemistry"],"023282":["information","engineering"],"027362":["foreign-languages"],"027372":["information","management"],"027382":["math-chemistry"],"027392":["information","engineering"],"027402":["earth-environment"],"027412":["social-psychology"],"027422":[],"027432":["engineering","health-medicine","life-science"],"031052":["education"],"041342":["information","engineering"],"041352":["information","management","finance-economics"],"041362":["law-politics"],"041372":["foreign-languages","literature-history-philosophy"],"041392":["social-psychology","mass-communication","law-politics","management"],"041412":["social-psychology"],"041402":["social-psychology","education","law-politics"],"041382":["math-chemistry","life-science","earth-environment"]}
